maxp/__init__.py
maxp/runtime.py
maxp-0.1.13.dist-info/LICENSE
maxp-0.1.13.dist-info/METADATA
maxp-0.1.13.dist-info/WHEEL
maxp-0.1.13.dist-info/top_level.txt
maxp-0.1.13.dist-info/RECORD
